{
    "Wolfs": {
        "Name": "3 Wolf",
        "Difficulty": 5
    },
    "RivalMerchant": {
        "Name": "Aganir, my merchant rival",
        "Difficulty": 8
    },
    "StarterDungeon": {
        "Name": "The Evil Tower of Rinaga",
        "Difficulty": 12
    },
    "Troll": {
        "Name": "The Troll of Dimaks",
        "Difficulty": 20
    },
    "WanderingWarrior": {
        "Name": "The Blade of Asmax",
        "Difficulty": 25
    },
    "Caravane": {
        "Name": "Raphael's Caravan",
        "Difficulty": 3
    },
    "BillionSlime": {
        "Name": "A billion slimes",
        "Difficulty": 1000
    },
    "Dragon": {
        "Name": "A Big White Dragon",
        "Difficulty": 80
    },
    "Dragon2": {
        "Name": "The Great Black Dragon with Red Eyes, Purple Nail Polish, Iridescent Scales and who distribute the gift of eyeliner",
        "Difficulty": 10
    }
}